MyAdmin.py
myadmin-1.0.0.dist-info/WHEEL
myadmin-1.0.0.dist-info/METADATA
myadmin-1.0.0.dist-info/RECORD
