Metadata-Version: 2.1
Name: myadmin
Version: 1.0.0
Summary: Make a PowerShell console in your python code. (With password.) Password: "223345"
Author: OwoNicoo
Author-email: 86409467+DiscordBotML@users.noreply.github.com
Requires-Python: >=3.9,<4.0
Classifier: Programming Language :: Python :: 3
Classifier: Programming Language :: Python :: 3.10
Classifier: Programming Language :: Python :: 3.9
